Metadata-Version: 2.1
Name: PyEmission
Version: 0.3.8
Summary: PyEmission is a Python library for the estimation of gasoline vehicular emissions and fuel consumption
Home-page: https://github.com/IdahoLabResearch/PyEmission
Author: Md Mamunur Rahman; Ruby Nguyen
Author-email: mdmamunur.rahman@inl.gov
License: Apache-2.0
Platform: UNKNOWN
Classifier: Programming Language :: Python
Classifier: Programming Language :: Python :: 3.7
